agentwallet/__init__.py
agentwallet/account.py
agentwallet/agent.py
agentwallet/api_client.py
agentwallet/exceptions.py
agentwallet/transaction.py
agentwallet/wallet.py
agentwallet-0.0.2.dist-info/LICENSE
agentwallet-0.0.2.dist-info/METADATA
agentwallet-0.0.2.dist-info/WHEEL
agentwallet-0.0.2.dist-info/top_level.txt
agentwallet-0.0.2.dist-info/RECORD
