Metadata-Version: 2.1
Name: agentwallet
Version: 0.0.2
Summary: Agent Wallet SDK.
Author-email: llmOS <llmos@llmos.dev>
License: 
Project-URL: homepage, https://www.llmos.dev/
Project-URL: repository, https://github.com/llmOS/agent-wallet-sdk/
Project-URL: documentation, https://docs.llmos.dev/
Requires-Python: >=3.10
License-File: LICENSE
Requires-Dist: requests >=2.31.0
